Metadata-Version: 2.1
Name: expsweep
Version: 0.0.3
Summary: sweep numerical experiment parameters and collect results in a Pandas table
Home-page: https://github.com/evidlo/expsweep
Author: Evan Widloski
Author-email: evan@evanw.org
License: MIT
Keywords: pandas pqdm
Platform: UNKNOWN
Classifier: Programming Language :: Python :: 3
License-File: LICENSE
